my_parser/__init__.py
my_parser/main.py
my_parser/common_functions/__init__.py
my_parser/common_functions/request_processing.py
my_parser/common_functions/url_processing.py
my_parser/parsers/__init__.py
my_parser/parsers/anchor_text_parser.py
my_parser/parsers/external_link_parser.py
my_parser/parsers/internal_link_parser.py
my_parser-0.1.dist-info/METADATA
my_parser-0.1.dist-info/WHEEL
my_parser-0.1.dist-info/top_level.txt
my_parser-0.1.dist-info/RECORD
