Metadata-Version: 2.1
Name: my-parser
Version: 0.1
Summary: This is module for parse some data from urls
Home-page: UNKNOWN
Author: aksenov
Author-email: UNKNOWN
License: UNKNOWN
Platform: UNKNOWN
